lribeiro.cherrypy.authorizer.neomodel-1.0.1-py3.4-nspkg.pth
lribeiro/cherrypy/authorizer/neomodel/__init__.py
lribeiro/cherrypy/authorizer/neomodel/models.py
lribeiro/cherrypy/authorizer/neomodel/auth.py
lribeiro.cherrypy.authorizer.neomodel-1.0.1.dist-info/WHEEL
lribeiro.cherrypy.authorizer.neomodel-1.0.1.dist-info/top_level.txt
lribeiro.cherrypy.authorizer.neomodel-1.0.1.dist-info/DESCRIPTION.rst
lribeiro.cherrypy.authorizer.neomodel-1.0.1.dist-info/namespace_packages.txt
lribeiro.cherrypy.authorizer.neomodel-1.0.1.dist-info/METADATA
lribeiro.cherrypy.authorizer.neomodel-1.0.1.dist-info/metadata.json
lribeiro.cherrypy.authorizer.neomodel-1.0.1.dist-info/RECORD
